DataProcessing_Package/DataProcessing.py
DataProcessing_Package/__init__.py
DataProcessing_Package_tewariutkarsh-0.0.1.dist-info/LICENSE
DataProcessing_Package_tewariutkarsh-0.0.1.dist-info/METADATA
DataProcessing_Package_tewariutkarsh-0.0.1.dist-info/WHEEL
DataProcessing_Package_tewariutkarsh-0.0.1.dist-info/top_level.txt
DataProcessing_Package_tewariutkarsh-0.0.1.dist-info/RECORD
