Metadata-Version: 2.1
Name: DataProcessing-Package-tewariutkarsh
Version: 0.0.1
Summary: This Package provides majorly Standard Scaling and various other functionalities.
Home-page: https://github.com/TewariUtkarsh/DataProcessing_Package
Author: Utkarsh
Author-email: tewariutkarsh@outlook.com
License: UNKNOWN
Project-URL: Bug Tracker, https://github.com/TewariUtkarsh/DataProcessing_Package/issues
Platform: UNKNOWN
Classifier: Programming Language :: Python :: 3
Classifier: License :: OSI Approved :: MIT License
Classifier: Operating System :: OS Independent
Requires-Python: >=3.6
License-File: LICENSE
